bakle_helpers/__init__.py
bakle_helpers/email.py
bakle_helpers/helper_exceptions.py
bakle_helpers/str.py
bakle_helpers/url.py
bakle_helpers/support/emails.txt
bakle_helpers/support/urls.txt
Bakle_Helpers-0.1.3.dist-info/LICENSE
Bakle_Helpers-0.1.3.dist-info/METADATA
Bakle_Helpers-0.1.3.dist-info/WHEEL
Bakle_Helpers-0.1.3.dist-info/top_level.txt
Bakle_Helpers-0.1.3.dist-info/RECORD
