Metadata-Version: 2.1
Name: Bakle-Helpers
Version: 0.1.3
Summary: Package that provides multiple helpers
Home-page: https://github.com/bakle/Py-Helpers
Author: Bashir Akle
Author-email: bashir.akle@gmail.com
License: UNKNOWN
Platform: UNKNOWN
License-File: LICENSE
